{
  "title": "Lesson5",
  "mode": "tracing",
  "lecture": [
		{
			"person": "teacher",
			"speech": "This time, I'll teach you about repetitions."
		},
		{
			"person": "child",
			"speech": "It's hard to make long music..."
		},
		{
			"person": "teacher",
			"speech": "Then, why don't you use repetitions?"
		},
		{
			"person": "child",
			"speech": "Repetitions? Does it mean using same phrase more than 2 times?"
		},
		{
			"person": "teacher",
			"speech": "That's right! It makes easier to make music!"
		},
		{
			"person": "child",
			"speech": "I can make long music very easily!"
		},
		{
			"person": "teacher",
			"speech": "Yes! Let's make music using repetitions!"
		}
  ],
  "music": {"C5":[],"B4":[],"A4":[],"G4":[],"F4":[],"E4":[],"D4":[],"C4":[],"B3":[],"A3":[],"G3":[{"pitch":"G3","unitNote":8,"start":4,"extension":3},{"pitch":"G3","unitNote":8,"start":12,"extension":3},{"pitch":"G3","unitNote":8,"start":20,"extension":1},{"pitch":"G3","unitNote":8,"start":22,"extension":1}],"F3":[{"pitch":"F3","unitNote":8,"start":3,"extension":0},{"pitch":"F3","unitNote":8,"start":11,"extension":0},{"pitch":"F3","unitNote":8,"start":19,"extension":0}],"E3":[{"pitch":"E3","unitNote":8,"start":2,"extension":0},{"pitch":"E3","unitNote":8,"start":10,"extension":0},{"pitch":"E3","unitNote":8,"start":18,"extension":0}],"D3":[{"pitch":"D3","unitNote":8,"start":1,"extension":0},{"pitch":"D3","unitNote":8,"start":9,"extension":0},{"pitch":"D3","unitNote":8,"start":17,"extension":0}],"C3":[{"pitch":"C3","unitNote":8,"start":0,"extension":0},{"pitch":"C3","unitNote":8,"start":8,"extension":0},{"pitch":"C3","unitNote":8,"start":16,"extension":0},{"pitch":"C3","unitNote":8,"start":24,"extension":7}],"B2":[],"A2":[],"G2":[],"F2":[],"E2":[],"D2":[],"C2":[]},
  "next": "Lesson5-2",
  "passNext": false
}
